honeybee_radiance_recipe/__init__.py
honeybee_radiance_recipe/cli.py
honeybee_radiance_recipe/recipe_helper.py
honeybee_radiance_recipe/annual_daylight/__init__.py
honeybee_radiance_recipe/annual_daylight/annual_daylight.py
honeybee_radiance_recipe/annual_daylight/annual_daylight_flow/__init__.py
honeybee_radiance_recipe/annual_daylight/annual_daylight_flow/main.py
honeybee_radiance_recipe/annual_daylight/annual_daylight_flow/dependencies/__init__.py
honeybee_radiance_recipe/annual_daylight/annual_daylight_flow/dependencies/annual_daylight_entry.py
honeybee_radiance_recipe/daylight_factor/__init__.py
honeybee_radiance_recipe/daylight_factor/daylight_factor.py
honeybee_radiance_recipe/daylight_factor/daylight_factor_flow/__init__.py
honeybee_radiance_recipe/daylight_factor/daylight_factor_flow/main.py
honeybee_radiance_recipe/daylight_factor/daylight_factor_flow/dependencies/__init__.py
honeybee_radiance_recipe/daylight_factor/daylight_factor_flow/dependencies/ray_tracing.py
honeybee_radiance_recipe-0.4.28.dist-info/LICENSE
honeybee_radiance_recipe-0.4.28.dist-info/METADATA
honeybee_radiance_recipe-0.4.28.dist-info/WHEEL
honeybee_radiance_recipe-0.4.28.dist-info/entry_points.txt
honeybee_radiance_recipe-0.4.28.dist-info/top_level.txt
honeybee_radiance_recipe-0.4.28.dist-info/RECORD
