Metadata-Version: 2.1
Name: honeybee-radiance-recipe
Version: 0.4.28
Summary: Collection of recipes for running daylight studies using honeybee-radiance.
Home-page: https://github.com/ladybug-tools/honeybee-radiance-recipe
Author: Ladybug Tools
Author-email: info@ladybug.tools
License: AGPL-3.0
Platform: UNKNOWN
Classifier: Programming Language :: Python :: 3.7
Classifier: Programming Language :: Python :: Implementation :: CPython
Classifier: License :: OSI Approved :: GNU Affero General Public License v3
Classifier: Operating System :: OS Independent
Requires-Dist: luigi (==3.0.2)
Requires-Dist: honeybee-radiance (==1.29.11)
Requires-Dist: click (==7.1.2)
